coderzparadise/__init__.py
coderzparadise/binarysearchtree.py
coderzparadise/disjointforrestset.py
coderzparadise/graph.py
coderzparadise/hashmap.py
coderzparadise/heap.py
coderzparadise/linked_list.py
coderzparadise/queue.py
coderzparadise/stack.py
coderzparadise/trie.py
coderzparadise-0.9.21.dist-info/METADATA
coderzparadise-0.9.21.dist-info/WHEEL
coderzparadise-0.9.21.dist-info/top_level.txt
coderzparadise-0.9.21.dist-info/RECORD
