Metadata-Version: 2.4
Name: coderzparadise
Version: 0.9.21
Summary: Welcome to coding in paradise!
Author-email: Coderz Paradise <coderzparadise@gmail.com>
Project-URL: Homepage, https://github.com/coderzparadise/coderzparadise/tree/main/src/coderzparadise
Project-URL: Issues, https://github.com/coderzparadise/coderzparadise/tree/main/src/coderzparadise
Keywords: data structures,coderz paradise,python,developers,AI,made easy,simple,fundamental,binary search tree,bst,disjoint set forest,disjoint set,union find,graph,adjacency list,adjacency list,adjacency matrix,adjacency matrix,edge list,edge list,hash map,hashmap,dictionary,heap,priority queue,linked list,queue,set,stack,trie,tree
Classifier: Programming Language :: Python :: 3
Classifier: Operating System :: OS Independent
Requires-Python: >=3.9
